{"id":756681,"cast":[{"adult":false,"gender":1,"id":10916,"known_for_department":"Acting","name":"Caterina Murino","original_name":"Caterina Murino","popularity":9.335,"profile_path":"/qwCb6uM20i0sg8N4RZges97keUk.jpg","cast_id":6,"character":"","credit_id":"5f931d60957ce5004d399ea1","order":1},{"adult":false,"gender":2,"id":74488,"known_for_department":"Acting","name":"Cosimo Fusco","original_name":"Cosimo Fusco","popularity":4.493,"profile_path":"/tzlLC0hxVspwBTMVB7x6mAuhnXV.jpg","cast_id":7,"character":"Dottore / Bufón","credit_id":"5f931d689661fc0033840a3d","order":2},{"adult":false,"gender":1,"id":1223239,"known_for_department":"Acting","name":"Ingrid García Jonsson","original_name":"Ingrid García Jonsson","popularity":12.578,"profile_path":"/gyv9JQOehJCHgtKzGq9FvLy3mSp.jpg","cast_id":8,"character":"Isa","credit_id":"5f931d71d768fe0042a073c8","order":3},{"adult":false,"gender":2,"id":1330941,"known_for_department":"Acting","name":"Nico Romero","original_name":"Nico Romero","popularity":6.907,"profile_path":"/zK0zTAaCxbaoE3C0nKvkZOdwWu6.jpg","cast_id":9,"character":"Alfonso","credit_id":"5f931d796d000c005194418b","order":4},{"adult":false,"gender":1,"id":588183,"known_for_department":"Acting","name":"Silvia Alonso","original_name":"Silvia Alonso","popularity":14.231,"profile_path":"/AgXsHxxSBOy9JmtWy5o8y3cKprY.jpg","cast_id":10,"character":"Susana","credit_id":"5f931d81d768fe0042a073e2","order":5},{"adult":false,"gender":2,"id":27392,"known_for_department":"Acting","name":"Enrico Lo Verso","original_name":"Enrico Lo Verso","popularity":1.788,"profile_path":"/riYINKQIv8mxYwtfj0L899K0iPu.jpg","cast_id":11,"character":"Giacomo","credit_id":"5f931d892b9320003374cf1c","order":6},{"adult":false,"gender":0,"id":66815,"known_for_department":"Acting","name":"Armando De Razza","original_name":"Armando De Razza","popularity":6.125,"profile_path":"/cc6jUaH7fTfcqASSmARdDUb0RaL.jpg","cast_id":12,"character":"Brunelli","credit_id":"5f931d922b9320005074cf10","order":7},{"adult":false,"gender":0,"id":2221708,"known_for_department":"Acting","name":"Nicolás Illoro","original_name":"Nicolás Illoro","popularity":1.246,"profile_path":"/gOPwiwZm5bfRlAiKog5S1FlipzB.jpg","cast_id":13,"character":"Javi","credit_id":"5f931d998805510042c18380","order":8},{"adult":false,"gender":0,"id":2695935,"known_for_department":"Acting","name":"Goize Blanco","original_name":"Goize Blanco","popularity":1.252,"profile_path":"/skfqY1f2V2ev2oE4AmwMBbGg2oE.jpg","cast_id":14,"character":"Arantza","credit_id":"5f931da6957ce5004039a233","order":9},{"adult":false,"gender":0,"id":2131824,"known_for_department":"Acting","name":"Alberto Bang","original_name":"Alberto Bang","popularity":2.213,"profile_path":"/1bPziV1KmbMKaROxGPwYC19DELF.jpg","cast_id":15,"character":"José","credit_id":"5f931daf7eb5f2005a00955c","order":10},{"adult":false,"gender":0,"id":128754,"known_for_department":"Acting","name":"Diego Pagotto","original_name":"Diego Pagotto","popularity":1.236,"profile_path":"/ua1jgVh15RDK2CLpTe1m8XdtQMd.jpg","cast_id":16,"character":"Salesman","credit_id":"6105bed0fdc1460073207857","order":11},{"adult":false,"gender":2,"id":48377,"known_for_department":"Acting","name":"Alessandro Bressanello","original_name":"Alessandro Bressanello","popularity":2.861,"profile_path":"/htcsjd0FVBorC69sRFbcoxgNbGa.jpg","cast_id":17,"character":"Colonna","credit_id":"6105bef7f96a39007432689f","order":12},{"adult":false,"gender":0,"id":2302672,"known_for_department":"Acting","name":"Giulia Pagnacco","original_name":"Giulia Pagnacco","popularity":1.96,"profile_path":"/u2k6ehUvps8fenlHpIA4CrXmNMI.jpg","cast_id":18,"character":"Gina","credit_id":"6105bf202a210c002b3f7f38","order":13}],"crew":[{"adult":false,"gender":2,"id":3788,"known_for_department":"Writing","name":"Jorge Guerricaechevarría","original_name":"Jorge Guerricaechevarría","popularity":1.632,"profile_path":"/qYQR7mQVKtDe4ojUxaCEK83689q.jpg","credit_id":"5f931d102a210c006d165163","department":"Writing","job":"Screenplay"},{"adult":false,"gender":2,"id":57865,"known_for_department":"Directing","name":"Álex de la Iglesia","original_name":"Álex de la Iglesia","popularity":1.035,"profile_path":"/vyZFSSNtY2jL06v4nJHLIT5fWa2.jpg","credit_id":"5f931d1a7eb5f200730093f0","department":"Writing","job":"Screenplay"},{"adult":false,"gender":2,"id":57865,"known_for_department":"Directing","name":"Álex de la Iglesia","original_name":"Álex de la Iglesia","popularity":1.035,"profile_path":"/vyZFSSNtY2jL06v4nJHLIT5fWa2.jpg","credit_id":"5f931cfb2b9320007b74cc9c","department":"Directing","job":"Director"},{"adult":false,"gender":2,"id":57865,"known_for_department":"Directing","name":"Álex de la Iglesia","original_name":"Álex de la Iglesia","popularity":1.035,"profile_path":"/vyZFSSNtY2jL06v4nJHLIT5fWa2.jpg","credit_id":"5f931d507e9d5f00514f132d","department":"Production","job":"Producer"},{"adult":false,"gender":1,"id":512958,"known_for_department":"Acting","name":"Carolina Bang","original_name":"Carolina Bang","popularity":3.37,"profile_path":"/hpiFsBwB2L1KDQZrQoAsFA1pl5d.jpg","credit_id":"5f931d3ed768fe005fa076f0","department":"Production","job":"Producer"}]}